shellrecharge-0.1.22.dist-info/METADATA
shellrecharge-0.1.22.dist-info/WHEEL
shellrecharge-0.1.22.dist-info/entry_points.txt
shellrecharge-0.1.22.dist-info/licenses/LICENSE
shellrecharge/__init__.py
shellrecharge/decorators.py
shellrecharge/models.py
shellrecharge/user.py
shellrecharge/usermodels.py
shellrecharge-0.1.22.dist-info/RECORD
