Metadata-Version: 2.1
Name: shellrecharge
Version: 0.1.22
Summary: Python 3 package to retrieve public and private EV charger data from Shell Recharge
Author-Email: cyberjunky <ron@cyberjunky.nl>
License: MIT
Classifier: Programming Language :: Python :: 3.10
Classifier: License :: OSI Approved :: GNU General Public License v3 or later (GPLv3+)
Project-URL: Homepage, https://github.com/cyberjunky/python-shellrecharge
Project-URL: Bug Tracker, https://github.com/cyberjunky/python-shellrecharge/issues
Requires-Python: >=3.10
Requires-Dist: aiohttp
Requires-Dist: aiohttp_retry
Requires-Dist: yarl
Requires-Dist: pydantic<3.0.0,>=1.0.0
Requires-Dist: bs4
